envsubst.py
envsubst-0.1.5.dist-info/LICENSE
envsubst-0.1.5.dist-info/METADATA
envsubst-0.1.5.dist-info/WHEEL
envsubst-0.1.5.dist-info/entry_points.txt
envsubst-0.1.5.dist-info/top_level.txt
envsubst-0.1.5.dist-info/RECORD
