Metadata-Version: 2.1
Name: envsubst
Version: 0.1.5
Summary: Substitute environment variables in a string
Home-page: https://github.com/ashafer01/python-envsubst
Author: Alex Shafer
Author-email: ashafer@pm.me
License: MIT
Platform: UNKNOWN
